DatabricksSparkZhishiku/README.md
DatabricksSparkZhishiku/__init__.py
DatabricksSparkZhishiku/__main__.py
DatabricksSparkZhishiku/file.epub
DatabricksSparkZhishiku/index.html
DatabricksSparkZhishiku/css/__init__.py
DatabricksSparkZhishiku/css/annotations.css
DatabricksSparkZhishiku/css/main.css
DatabricksSparkZhishiku/css/normalize.css
DatabricksSparkZhishiku/css/popup.css
DatabricksSparkZhishiku/font/__init__.py
DatabricksSparkZhishiku/font/fontello.eot
DatabricksSparkZhishiku/font/fontello.svg
DatabricksSparkZhishiku/font/fontello.ttf
DatabricksSparkZhishiku/font/fontello.woff
DatabricksSparkZhishiku/img/__init__.py
DatabricksSparkZhishiku/img/annotator-glyph-sprite.png
DatabricksSparkZhishiku/img/annotator-icon-sprite.png
DatabricksSparkZhishiku/img/apple-touch-icon.png
DatabricksSparkZhishiku/img/cancelfullscreen.png
DatabricksSparkZhishiku/img/close.png
DatabricksSparkZhishiku/img/fullscreen.png
DatabricksSparkZhishiku/img/loader.gif
DatabricksSparkZhishiku/img/menu-icon.png
DatabricksSparkZhishiku/img/save.png
DatabricksSparkZhishiku/img/saved.png
DatabricksSparkZhishiku/img/settings-s.png
DatabricksSparkZhishiku/img/settings.png
DatabricksSparkZhishiku/img/star.png
DatabricksSparkZhishiku/js/__init__.py
DatabricksSparkZhishiku/js/epub.js
DatabricksSparkZhishiku/js/epub.min.js
DatabricksSparkZhishiku/js/epub.min.map
DatabricksSparkZhishiku/js/hooks.min.js
DatabricksSparkZhishiku/js/hooks.min.map
DatabricksSparkZhishiku/js/reader.js
DatabricksSparkZhishiku/js/reader.js.map
DatabricksSparkZhishiku/js/reader.min.js
DatabricksSparkZhishiku/js/reader.min.map
DatabricksSparkZhishiku/js/hooks/__init__.py
DatabricksSparkZhishiku/js/hooks/extensions/__init__.py
DatabricksSparkZhishiku/js/hooks/extensions/highlight.js
DatabricksSparkZhishiku/js/libs/__init__.py
DatabricksSparkZhishiku/js/libs/jquery.min.js
DatabricksSparkZhishiku/js/libs/localforage.min.js
DatabricksSparkZhishiku/js/libs/screenfull.js
DatabricksSparkZhishiku/js/libs/screenfull.min.js
databricks_spark_zhishiku-2024.3.4.0.dist-info/METADATA
databricks_spark_zhishiku-2024.3.4.0.dist-info/WHEEL
databricks_spark_zhishiku-2024.3.4.0.dist-info/entry_points.txt
databricks_spark_zhishiku-2024.3.4.0.dist-info/top_level.txt
databricks_spark_zhishiku-2024.3.4.0.dist-info/RECORD
